{
  "boards": [
    {
      "name": "novy board task #13",
      "user": 0,
      "id": 81199267822,
      "starred": false,
      "created": "2022-11-21"
    },
    {
      "name": "verejny board",
      "user": 0,
      "id": 18655014692,
      "starred": false,
      "created": "2022-11-21"
    },
    {
      "name": "private board",
      "user": 1,
      "id": 56202253883,
      "starred": false,
      "created": "2022-11-21"
    },
    {
      "name": "task #20",
      "user": 0,
      "id": 83070376571,
      "starred": false,
      "created": "2022-11-21"
    }
  ],
  "tasks": [
    {
      "boardId": 18655014692,
      "description": "",
      "completed": false,
      "listId": 83807222145,
      "title": "commnad tasks",
      "id": 9566273229,
      "created": "2022-11-21",
      "deadline": "2022-11-24"
    },
    {
      "boardId": 83070376571,
      "description": "",
      "completed": false,
      "listId": 85302899383,
      "title": "tasklist2",
      "id": 19823524703,
      "created": "2022-11-21",
      "deadline": "2022-11-24",
      "order": 0
    },
    {
      "boardId": 83070376571,
      "description": "",
      "completed": false,
      "listId": 85302899383,
      "title": "1",
      "id": 68934030871,
      "created": "2022-11-21",
      "deadline": "2022-11-24",
      "order": 1
    },
    {
      "boardId": 83070376571,
      "description": "",
      "completed": false,
      "listId": 34926036844,
      "title": "tt",
      "id": 56057148197,
      "created": "2022-11-21",
      "deadline": "2022-11-24"
    }
  ],
  "users": [],
  "lists": [
    {
      "title": "list cez API",
      "boardId": 81199267822,
      "id": 56705074924,
      "created": "2022-11-21"
    },
    {
      "boardId": 18655014692,
      "title": "public lists",
      "id": 83807222145,
      "created": "2022-11-21"
    },
    {
      "boardId": 83070376571,
      "title": "list1",
      "id": 34926036844,
      "created": "2022-11-21",
      "order": 0
    },
    {
      "boardId": 83070376571,
      "title": "list2",
      "id": 85302899383,
      "created": "2022-11-21",
      "order": 1
    }
  ]
}